hydra_plugins/hydra_msc_plugin/__init__.py
multi_storage_client-0.41.0.dist-info/METADATA
multi_storage_client-0.41.0.dist-info/WHEEL
multi_storage_client-0.41.0.dist-info/entry_points.txt
multistorageclient/__init__.py
multistorageclient/cache.py
multistorageclient/caching/README.md
multistorageclient/caching/__init__.py
multistorageclient/caching/cache_config.py
multistorageclient/caching/cache_item.py
multistorageclient/caching/eviction_policy.py
multistorageclient/client/__init__.py
multistorageclient/client/client.py
multistorageclient/client/composite.py
multistorageclient/client/single.py
multistorageclient/client/types.py
multistorageclient/commands/__init__.py
multistorageclient/commands/cli/__init__.py
multistorageclient/commands/cli/actions/__init__.py
multistorageclient/commands/cli/actions/action.py
multistorageclient/commands/cli/actions/config.py
multistorageclient/commands/cli/actions/help.py
multistorageclient/commands/cli/actions/ls.py
multistorageclient/commands/cli/actions/mcp_server.py
multistorageclient/commands/cli/actions/rm.py
multistorageclient/commands/cli/actions/sync.py
multistorageclient/commands/cli/actions/utils.py
multistorageclient/commands/cli/main.py
multistorageclient/commands/msc_benchmark.py
multistorageclient/config.py
multistorageclient/constants.py
multistorageclient/contrib/__init__.py
multistorageclient/contrib/async_fs.py
multistorageclient/contrib/hydra.py
multistorageclient/contrib/numpy.py
multistorageclient/contrib/os/__init__.py
multistorageclient/contrib/os/path.py
multistorageclient/contrib/pickle.py
multistorageclient/contrib/ray/__init__.py
multistorageclient/contrib/ray/utils.py
multistorageclient/contrib/torch/__init__.py
multistorageclient/contrib/torch/core.py
multistorageclient/contrib/torch/filesystem.py
multistorageclient/contrib/xarray.py
multistorageclient/contrib/zarr.py
multistorageclient/file.py
multistorageclient/generators/__init__.py
multistorageclient/generators/manifest_metadata.py
multistorageclient/instrumentation/__init__.py
multistorageclient/instrumentation/auth.py
multistorageclient/instrumentation/utils.py
multi_storage_client-0.41.0.dist-info/RECORD
